MANIFEST.in
README.md
setup.py
src/m3_pushme.egg-info/PKG-INFO
src/m3_pushme.egg-info/SOURCES.txt
src/m3_pushme.egg-info/dependency_links.txt
src/m3_pushme.egg-info/requires.txt
src/m3_pushme.egg-info/top_level.txt
src/pushme/__init__.py
src/pushme/client.py
src/pushme/example.html
src/pushme/options.py
src/pushme/queue.py
src/pushme/server.py
src/pushme/demo/__init__.py
src/pushme/demo/actions.py
src/pushme/demo/app_meta.py
src/pushme/demo/ui.py
src/pushme/demo/templates/msgwindow.js
src/pushme/mq/__init__.py
src/pushme/mq/backend_snakemq.py
src/pushme/mq/interface.py
src/pushme/static/pushme.js
src/pushme/static/sockjs-0.3.min.js