Metadata-Version: 1.1
Name: m3-pushme
Version: 0.1.5
Summary: Подсистема доставки сообщений от сервера браузеру
Home-page: https://bitbucket.org/barsgroup/pushme
Author: Alexey Pirogov
Author-email: pirogov@bars-open.ru
License: MIT
Platform: UNKNOWN
Classifier: Intended Audience :: Developers
Classifier: Environment :: Web Environment
Classifier: Natural Language :: Russian
Classifier: Natural Language :: English
Classifier: Operating System :: OS Independent
Classifier: Programming Language :: Python
Classifier: License :: OSI Approved :: MIT License
Classifier: Development Status :: 5 - Production/Stable
